MANIFEST.in
README.rst
setup.cfg
setup.py
aranha/__init__.py
aranha/crawler.py
aranha/handler.py
aranha/job.py
aranha/simple.py
aranha/utils.py
aranha.egg-info/PKG-INFO
aranha.egg-info/SOURCES.txt
aranha.egg-info/dependency_links.txt
aranha.egg-info/entry_points.txt
aranha.egg-info/not-zip-safe
aranha.egg-info/requires.txt
aranha.egg-info/top_level.txt