Metadata-Version: 1.0
Name: aranha
Version: 0.1.1
Summary: simple gevent based web spider and tools
Home-page: http://github.com/jmoiron/aranha
Author: Jason Moiron
Author-email: jmoiron@jmoiron.net
License: MIT
Keywords: python gevent spider
Platform: UNKNOWN
Classifier: Development Status :: 3 - Alpha
